{"schedules":[{"arriveTime":{"day":4,"hour":12,"minute":38},"nameShip":"PI","cargo":{"cargoType":"CONTAINER","weight":5745},"unloadDuration":{"day":0,"hour":0,"minute":58}},{"arriveTime":{"day":3,"hour":15,"minute":25},"nameShip":"BP","cargo":{"cargoType":"LIQUID","weight":69844},"unloadDuration":{"day":0,"hour":14,"minute":55}},{"arriveTime":{"day":10,"hour":3,"minute":34},"nameShip":"QPOY","cargo":{"cargoType":"LIQUID","weight":59848},"unloadDuration":{"day":0,"hour":12,"minute":47}},{"arriveTime":{"day":18,"hour":8,"minute":29},"nameShip":"FCP","cargo":{"cargoType":"CONTAINER","weight":5525},"unloadDuration":{"day":0,"hour":0,"minute":55}},{"arriveTime":{"day":25,"hour":3,"minute":31},"nameShip":"GM","cargo":{"cargoType":"LOOSE","weight":54329},"unloadDuration":{"day":0,"hour":13,"minute":55}},{"arriveTime":{"day":8,"hour":1,"minute":57},"nameShip":"XX","cargo":{"cargoType":"CONTAINER","weight":3265},"unloadDuration":{"day":0,"hour":0,"minute":32}},{"arriveTime":{"day":12,"hour":22,"minute":22},"nameShip":"RN","cargo":{"cargoType":"LOOSE","weight":41374},"unloadDuration":{"day":0,"hour":10,"minute":36}},{"arriveTime":{"day":17,"hour":16,"minute":41},"nameShip":"JK","cargo":{"cargoType":"LOOSE","weight":42213},"unloadDuration":{"day":0,"hour":10,"minute":49}},{"arriveTime":{"day":16,"hour":17,"minute":51},"nameShip":"MCN","cargo":{"cargoType":"LOOSE","weight":58057},"unloadDuration":{"day":0,"hour":14,"minute":53}},{"arriveTime":{"day":9,"hour":21,"minute":46},"nameShip":"GRC","cargo":{"cargoType":"LOOSE","weight":50991},"unloadDuration":{"day":0,"hour":13,"minute":4}},{"arriveTime":{"day":7,"hour":1,"minute":2},"nameShip":"FX","cargo":{"cargoType":"LOOSE","weight":51288},"unloadDuration":{"day":0,"hour":13,"minute":9}},{"arriveTime":{"day":24,"hour":6,"minute":27},"nameShip":"OECH","cargo":{"cargoType":"LIQUID","weight":60607},"unloadDuration":{"day":0,"hour":12,"minute":57}},{"arriveTime":{"day":7,"hour":20,"minute":17},"nameShip":"QI","cargo":{"cargoType":"LOOSE","weight":50418},"unloadDuration":{"day":0,"hour":12,"minute":55}},{"arriveTime":{"day":4,"hour":4,"minute":15},"nameShip":"FF","cargo":{"cargoType":"LIQUID","weight":55613},"unloadDuration":{"day":0,"hour":11,"minute":52}},{"arriveTime":{"day":21,"hour":19,"minute":1},"nameShip":"GTMI","cargo":{"cargoType":"LOOSE","weight":40313},"unloadDuration":{"day":0,"hour":10,"minute":20}},{"arriveTime":{"day":15,"hour":20,"minute":56},"nameShip":"EDJI","cargo":{"cargoType":"CONTAINER","weight":2374},"unloadDuration":{"day":0,"hour":0,"minute":23}},{"arriveTime":{"day":21,"hour":18,"minute":21},"nameShip":"FV","cargo":{"cargoType":"CONTAINER","weight":3599},"unloadDuration":{"day":0,"hour":0,"minute":36}},{"arriveTime":{"day":11,"hour":0,"minute":46},"nameShip":"BTI","cargo":{"cargoType":"LOOSE","weight":59708},"unloadDuration":{"day":0,"hour":15,"minute":18}},{"arriveTime":{"day":17,"hour":19,"minute":47},"nameShip":"ZEP","cargo":{"cargoType":"LIQUID","weight":63308},"unloadDuration":{"day":0,"hour":13,"minute":31}},{"arriveTime":{"day":22,"hour":12,"minute":47},"nameShip":"OOIX","cargo":{"cargoType":"LIQUID","weight":55557},"unloadDuration":{"day":0,"hour":11,"minute":52}},{"arriveTime":{"day":6,"hour":6,"minute":4},"nameShip":"SXD","cargo":{"cargoType":"LOOSE","weight":41735},"unloadDuration":{"day":0,"hour":10,"minute":42}},{"arriveTime":{"day":17,"hour":21,"minute":32},"nameShip":"VC","cargo":{"cargoType":"LOOSE","weight":44225},"unloadDuration":{"day":0,"hour":11,"minute":20}},{"arriveTime":{"day":2,"hour":13,"minute":59},"nameShip":"QND","cargo":{"cargoType":"LOOSE","weight":45662},"unloadDuration":{"day":0,"hour":11,"minute":42}},{"arriveTime":{"day":17,"hour":0,"minute":52},"nameShip":"ZC","cargo":{"cargoType":"CONTAINER","weight":4060},"unloadDuration":{"day":0,"hour":0,"minute":41}},{"arriveTime":{"day":12,"hour":16,"minute":34},"nameShip":"MAJB","cargo":{"cargoType":"LOOSE","weight":48119},"unloadDuration":{"day":0,"hour":12,"minute":20}},{"arriveTime":{"day":22,"hour":18,"minute":3},"nameShip":"VZ","cargo":{"cargoType":"LIQUID","weight":63498},"unloadDuration":{"day":0,"hour":13,"minute":34}},{"arriveTime":{"day":2,"hour":12,"minute":4},"nameShip":"TWX","cargo":{"cargoType":"LIQUID","weight":63924},"unloadDuration":{"day":0,"hour":13,"minute":39}},{"arriveTime":{"day":12,"hour":22,"minute":12},"nameShip":"DNFA","cargo":{"cargoType":"LIQUID","weight":61058},"unloadDuration":{"day":0,"hour":13,"minute":2}},{"arriveTime":{"day":0,"hour":15,"minute":58},"nameShip":"COBN","cargo":{"cargoType":"CONTAINER","weight":5854},"unloadDuration":{"day":0,"hour":0,"minute":59}},{"arriveTime":{"day":22,"hour":21,"minute":21},"nameShip":"CQMX","cargo":{"cargoType":"LOOSE","weight":44633},"unloadDuration":{"day":0,"hour":11,"minute":26}},{"arriveTime":{"day":8,"hour":3,"minute":14},"nameShip":"EEP","cargo":{"cargoType":"LOOSE","weight":58777},"unloadDuration":{"day":0,"hour":15,"minute":4}},{"arriveTime":{"day":15,"hour":19,"minute":23},"nameShip":"NTWH","cargo":{"cargoType":"CONTAINER","weight":5898},"unloadDuration":{"day":0,"hour":0,"minute":59}},{"arriveTime":{"day":18,"hour":12,"minute":49},"nameShip":"JK","cargo":{"cargoType":"LOOSE","weight":44234},"unloadDuration":{"day":0,"hour":11,"minute":20}},{"arriveTime":{"day":15,"hour":8,"minute":9},"nameShip":"QFJM","cargo":{"cargoType":"LIQUID","weight":52413},"unloadDuration":{"day":0,"hour":11,"minute":11}},{"arriveTime":{"day":10,"hour":11,"minute":33},"nameShip":"DCL","cargo":{"cargoType":"LOOSE","weight":41331},"unloadDuration":{"day":0,"hour":10,"minute":35}},{"arriveTime":{"day":18,"hour":1,"minute":22},"nameShip":"UNPI","cargo":{"cargoType":"LIQUID","weight":59922},"unloadDuration":{"day":0,"hour":12,"minute":48}},{"arriveTime":{"day":17,"hour":11,"minute":4},"nameShip":"DK","cargo":{"cargoType":"LOOSE","weight":58128},"unloadDuration":{"day":0,"hour":14,"minute":54}},{"arriveTime":{"day":15,"hour":20,"minute":19},"nameShip":"KY","cargo":{"cargoType":"LOOSE","weight":49853},"unloadDuration":{"day":0,"hour":12,"minute":46}},{"arriveTime":{"day":1,"hour":19,"minute":30},"nameShip":"PJMG","cargo":{"cargoType":"LOOSE","weight":54640},"unloadDuration":{"day":0,"hour":14,"minute":0}},{"arriveTime":{"day":2,"hour":23,"minute":50},"nameShip":"GDK","cargo":{"cargoType":"CONTAINER","weight":4909},"unloadDuration":{"day":0,"hour":0,"minute":49}},{"arriveTime":{"day":14,"hour":10,"minute":58},"nameShip":"NYC","cargo":{"cargoType":"CONTAINER","weight":5668},"unloadDuration":{"day":0,"hour":0,"minute":57}},{"arriveTime":{"day":8,"hour":3,"minute":48},"nameShip":"FEGA","cargo":{"cargoType":"CONTAINER","weight":5943},"unloadDuration":{"day":0,"hour":1,"minute":0}},{"arriveTime":{"day":14,"hour":22,"minute":33},"nameShip":"UVVR","cargo":{"cargoType":"CONTAINER","weight":2289},"unloadDuration":{"day":0,"hour":0,"minute":23}},{"arriveTime":{"day":18,"hour":5,"minute":30},"nameShip":"NE","cargo":{"cargoType":"LIQUID","weight":65527},"unloadDuration":{"day":0,"hour":14,"minute":0}},{"arriveTime":{"day":13,"hour":1,"minute":0},"nameShip":"WDT","cargo":{"cargoType":"CONTAINER","weight":3522},"unloadDuration":{"day":0,"hour":0,"minute":35}},{"arriveTime":{"day":28,"hour":4,"minute":56},"nameShip":"BV","cargo":{"cargoType":"LIQUID","weight":50595},"unloadDuration":{"day":0,"hour":10,"minute":48}},{"arriveTime":{"day":19,"hour":17,"minute":19},"nameShip":"RSM","cargo":{"cargoType":"LIQUID","weight":56370},"unloadDuration":{"day":0,"hour":12,"minute":2}},{"arriveTime":{"day":5,"hour":3,"minute":10},"nameShip":"MLU","cargo":{"cargoType":"CONTAINER","weight":3882},"unloadDuration":{"day":0,"hour":0,"minute":39}},{"arriveTime":{"day":9,"hour":4,"minute":28},"nameShip":"AO","cargo":{"cargoType":"CONTAINER","weight":2529},"unloadDuration":{"day":0,"hour":0,"minute":25}},{"arriveTime":{"day":7,"hour":10,"minute":18},"nameShip":"GPUC","cargo":{"cargoType":"LIQUID","weight":62639},"unloadDuration":{"day":0,"hour":13,"minute":23}},{"arriveTime":{"day":9,"hour":16,"minute":19},"nameShip":"SA","cargo":{"cargoType":"LIQUID","weight":66047},"unloadDuration":{"day":0,"hour":14,"minute":6}},{"arriveTime":{"day":0,"hour":1,"minute":53},"nameShip":"VRVT","cargo":{"cargoType":"CONTAINER","weight":5861},"unloadDuration":{"day":0,"hour":0,"minute":59}},{"arriveTime":{"day":20,"hour":2,"minute":14},"nameShip":"CEHT","cargo":{"cargoType":"LIQUID","weight":53688},"unloadDuration":{"day":0,"hour":11,"minute":28}},{"arriveTime":{"day":13,"hour":22,"minute":0},"nameShip":"RNFJ","cargo":{"cargoType":"CONTAINER","weight":4485},"unloadDuration":{"day":0,"hour":0,"minute":45}},{"arriveTime":{"day":12,"hour":0,"minute":18},"nameShip":"SD","cargo":{"cargoType":"LOOSE","weight":54267},"unloadDuration":{"day":0,"hour":13,"minute":54}},{"arriveTime":{"day":3,"hour":20,"minute":20},"nameShip":"KH","cargo":{"cargoType":"LIQUID","weight":54220},"unloadDuration":{"day":0,"hour":11,"minute":35}},{"arriveTime":{"day":5,"hour":18,"minute":13},"nameShip":"RB","cargo":{"cargoType":"CONTAINER","weight":5127},"unloadDuration":{"day":0,"hour":0,"minute":51}},{"arriveTime":{"day":17,"hour":2,"minute":9},"nameShip":"DTK","cargo":{"cargoType":"LIQUID","weight":64326},"unloadDuration":{"day":0,"hour":13,"minute":44}},{"arriveTime":{"day":25,"hour":5,"minute":51},"nameShip":"UV","cargo":{"cargoType":"LIQUID","weight":50628},"unloadDuration":{"day":0,"hour":10,"minute":49}},{"arriveTime":{"day":14,"hour":22,"minute":39},"nameShip":"ZK","cargo":{"cargoType":"CONTAINER","weight":2327},"unloadDuration":{"day":0,"hour":0,"minute":23}},{"arriveTime":{"day":28,"hour":2,"minute":4},"nameShip":"OD","cargo":{"cargoType":"LIQUID","weight":54312},"unloadDuration":{"day":0,"hour":11,"minute":36}},{"arriveTime":{"day":21,"hour":3,"minute":1},"nameShip":"EKJ","cargo":{"cargoType":"LIQUID","weight":56418},"unloadDuration":{"day":0,"hour":12,"minute":3}},{"arriveTime":{"day":27,"hour":15,"minute":14},"nameShip":"YGW","cargo":{"cargoType":"LIQUID","weight":61043},"unloadDuration":{"day":0,"hour":13,"minute":2}},{"arriveTime":{"day":25,"hour":20,"minute":21},"nameShip":"TJJU","cargo":{"cargoType":"LIQUID","weight":69053},"unloadDuration":{"day":0,"hour":14,"minute":45}},{"arriveTime":{"day":20,"hour":22,"minute":22},"nameShip":"OE","cargo":{"cargoType":"LIQUID","weight":52922},"unloadDuration":{"day":0,"hour":11,"minute":18}},{"arriveTime":{"day":17,"hour":7,"minute":12},"nameShip":"QGPU","cargo":{"cargoType":"LIQUID","weight":62867},"unloadDuration":{"day":0,"hour":13,"minute":25}},{"arriveTime":{"day":3,"hour":18,"minute":37},"nameShip":"OJFJ","cargo":{"cargoType":"LIQUID","weight":66170},"unloadDuration":{"day":0,"hour":14,"minute":8}},{"arriveTime":{"day":15,"hour":12,"minute":7},"nameShip":"PY","cargo":{"cargoType":"LOOSE","weight":43486},"unloadDuration":{"day":0,"hour":11,"minute":9}},{"arriveTime":{"day":24,"hour":15,"minute":19},"nameShip":"RK","cargo":{"cargoType":"LIQUID","weight":62875},"unloadDuration":{"day":0,"hour":13,"minute":26}},{"arriveTime":{"day":5,"hour":11,"minute":54},"nameShip":"CUB","cargo":{"cargoType":"LIQUID","weight":61898},"unloadDuration":{"day":0,"hour":13,"minute":13}},{"arriveTime":{"day":15,"hour":20,"minute":21},"nameShip":"GJG","cargo":{"cargoType":"LIQUID","weight":69880},"unloadDuration":{"day":0,"hour":14,"minute":55}},{"arriveTime":{"day":24,"hour":8,"minute":31},"nameShip":"PDVT","cargo":{"cargoType":"CONTAINER","weight":2785},"unloadDuration":{"day":0,"hour":0,"minute":28}},{"arriveTime":{"day":29,"hour":20,"minute":21},"nameShip":"NRE","cargo":{"cargoType":"LIQUID","weight":60958},"unloadDuration":{"day":0,"hour":13,"minute":1}},{"arriveTime":{"day":29,"hour":9,"minute":13},"nameShip":"FUN","cargo":{"cargoType":"CONTAINER","weight":5708},"unloadDuration":{"day":0,"hour":0,"minute":57}},{"arriveTime":{"day":12,"hour":23,"minute":16},"nameShip":"SJV","cargo":{"cargoType":"LIQUID","weight":63893},"unloadDuration":{"day":0,"hour":13,"minute":39}},{"arriveTime":{"day":10,"hour":2,"minute":31},"nameShip":"GOSW","cargo":{"cargoType":"LOOSE","weight":40888},"unloadDuration":{"day":0,"hour":10,"minute":29}},{"arriveTime":{"day":14,"hour":10,"minute":12},"nameShip":"OQB","cargo":{"cargoType":"CONTAINER","weight":2057},"unloadDuration":{"day":0,"hour":0,"minute":20}},{"arriveTime":{"day":4,"hour":18,"minute":56},"nameShip":"PEIM","cargo":{"cargoType":"LOOSE","weight":44653},"unloadDuration":{"day":0,"hour":11,"minute":26}},{"arriveTime":{"day":21,"hour":2,"minute":10},"nameShip":"SZPU","cargo":{"cargoType":"LIQUID","weight":56944},"unloadDuration":{"day":0,"hour":12,"minute":10}},{"arriveTime":{"day":18,"hour":14,"minute":43},"nameShip":"XD","cargo":{"cargoType":"LIQUID","weight":59727},"unloadDuration":{"day":0,"hour":12,"minute":45}},{"arriveTime":{"day":6,"hour":15,"minute":25},"nameShip":"LR","cargo":{"cargoType":"CONTAINER","weight":3263},"unloadDuration":{"day":0,"hour":0,"minute":32}},{"arriveTime":{"day":20,"hour":15,"minute":29},"nameShip":"BCGF","cargo":{"cargoType":"LOOSE","weight":55209},"unloadDuration":{"day":0,"hour":14,"minute":9}},{"arriveTime":{"day":13,"hour":4,"minute":59},"nameShip":"BAQA","cargo":{"cargoType":"LIQUID","weight":67196},"unloadDuration":{"day":0,"hour":14,"minute":21}},{"arriveTime":{"day":8,"hour":11,"minute":57},"nameShip":"OBJ","cargo":{"cargoType":"LOOSE","weight":49752},"unloadDuration":{"day":0,"hour":12,"minute":45}},{"arriveTime":{"day":20,"hour":15,"minute":53},"nameShip":"IUVE","cargo":{"cargoType":"LOOSE","weight":41036},"unloadDuration":{"day":0,"hour":10,"minute":31}},{"arriveTime":{"day":13,"hour":8,"minute":55},"nameShip":"IARS","cargo":{"cargoType":"CONTAINER","weight":3855},"unloadDuration":{"day":0,"hour":0,"minute":38}},{"arriveTime":{"day":7,"hour":4,"minute":37},"nameShip":"IXIA","cargo":{"cargoType":"LIQUID","weight":65014},"unloadDuration":{"day":0,"hour":13,"minute":53}},{"arriveTime":{"day":15,"hour":8,"minute":47},"nameShip":"KYY","cargo":{"cargoType":"LIQUID","weight":59857},"unloadDuration":{"day":0,"hour":12,"minute":47}},{"arriveTime":{"day":13,"hour":3,"minute":41},"nameShip":"HJI","cargo":{"cargoType":"LIQUID","weight":68587},"unloadDuration":{"day":0,"hour":14,"minute":39}},{"arriveTime":{"day":28,"hour":11,"minute":46},"nameShip":"QCPW","cargo":{"cargoType":"CONTAINER","weight":3387},"unloadDuration":{"day":0,"hour":0,"minute":34}},{"arriveTime":{"day":20,"hour":0,"minute":20},"nameShip":"ND","cargo":{"cargoType":"LOOSE","weight":49878},"unloadDuration":{"day":0,"hour":12,"minute":47}},{"arriveTime":{"day":18,"hour":13,"minute":59},"nameShip":"ZW","cargo":{"cargoType":"CONTAINER","weight":4616},"unloadDuration":{"day":0,"hour":0,"minute":46}},{"arriveTime":{"day":1,"hour":12,"minute":36},"nameShip":"CIC","cargo":{"cargoType":"CONTAINER","weight":2713},"unloadDuration":{"day":0,"hour":0,"minute":27}},{"arriveTime":{"day":14,"hour":4,"minute":46},"nameShip":"YPGC","cargo":{"cargoType":"LOOSE","weight":59051},"unloadDuration":{"day":0,"hour":15,"minute":8}},{"arriveTime":{"day":23,"hour":22,"minute":13},"nameShip":"YAB","cargo":{"cargoType":"LOOSE","weight":49841},"unloadDuration":{"day":0,"hour":12,"minute":46}},{"arriveTime":{"day":10,"hour":14,"minute":28},"nameShip":"YXN","cargo":{"cargoType":"LIQUID","weight":57387},"unloadDuration":{"day":0,"hour":12,"minute":15}},{"arriveTime":{"day":13,"hour":23,"minute":27},"nameShip":"YIJ","cargo":{"cargoType":"LIQUID","weight":59656},"unloadDuration":{"day":0,"hour":12,"minute":44}},{"arriveTime":{"day":10,"hour":15,"minute":0},"nameShip":"IA","cargo":{"cargoType":"LIQUID","weight":65798},"unloadDuration":{"day":0,"hour":14,"minute":3}},{"arriveTime":{"day":15,"hour":23,"minute":23},"nameShip":"CWH","cargo":{"cargoType":"CONTAINER","weight":2962},"unloadDuration":{"day":0,"hour":0,"minute":29}},{"arriveTime":{"day":27,"hour":15,"minute":3},"nameShip":"ZL","cargo":{"cargoType":"LIQUID","weight":57970},"unloadDuration":{"day":0,"hour":12,"minute":23}},{"arriveTime":{"day":1,"hour":10,"minute":39},"nameShip":"RNES","cargo":{"cargoType":"LIQUID","weight":50487},"unloadDuration":{"day":0,"hour":10,"minute":47}},{"arriveTime":{"day":5,"hour":12,"minute":10},"nameShip":"EYQ","cargo":{"cargoType":"LIQUID","weight":61941},"unloadDuration":{"day":0,"hour":13,"minute":14}},{"arriveTime":{"day":6,"hour":19,"minute":39},"nameShip":"NVUU","cargo":{"cargoType":"LIQUID","weight":65915},"unloadDuration":{"day":0,"hour":14,"minute":5}},{"arriveTime":{"day":0,"hour":22,"minute":11},"nameShip":"DB","cargo":{"cargoType":"LOOSE","weight":47448},"unloadDuration":{"day":0,"hour":12,"minute":9}},{"arriveTime":{"day":15,"hour":10,"minute":15},"nameShip":"SXKF","cargo":{"cargoType":"CONTAINER","weight":5472},"unloadDuration":{"day":0,"hour":0,"minute":55}},{"arriveTime":{"day":4,"hour":7,"minute":13},"nameShip":"YF","cargo":{"cargoType":"LIQUID","weight":61918},"unloadDuration":{"day":0,"hour":13,"minute":13}},{"arriveTime":{"day":17,"hour":17,"minute":51},"nameShip":"GITT","cargo":{"cargoType":"CONTAINER","weight":4439},"unloadDuration":{"day":0,"hour":0,"minute":44}},{"arriveTime":{"day":15,"hour":6,"minute":40},"nameShip":"BC","cargo":{"cargoType":"LIQUID","weight":64606},"unloadDuration":{"day":0,"hour":13,"minute":48}},{"arriveTime":{"day":3,"hour":12,"minute":17},"nameShip":"CWL","cargo":{"cargoType":"CONTAINER","weight":3770},"unloadDuration":{"day":0,"hour":0,"minute":38}},{"arriveTime":{"day":19,"hour":10,"minute":53},"nameShip":"KSN","cargo":{"cargoType":"LOOSE","weight":46200},"unloadDuration":{"day":0,"hour":11,"minute":50}},{"arriveTime":{"day":10,"hour":9,"minute":13},"nameShip":"JBNK","cargo":{"cargoType":"CONTAINER","weight":2647},"unloadDuration":{"day":0,"hour":0,"minute":26}},{"arriveTime":{"day":20,"hour":13,"minute":55},"nameShip":"KIJ","cargo":{"cargoType":"CONTAINER","weight":5932},"unloadDuration":{"day":0,"hour":0,"minute":59}},{"arriveTime":{"day":28,"hour":15,"minute":56},"nameShip":"AFQB","cargo":{"cargoType":"CONTAINER","weight":3263},"unloadDuration":{"day":0,"hour":0,"minute":32}},{"arriveTime":{"day":18,"hour":6,"minute":52},"nameShip":"ZU","cargo":{"cargoType":"LIQUID","weight":51767},"unloadDuration":{"day":0,"hour":11,"minute":3}},{"arriveTime":{"day":4,"hour":5,"minute":22},"nameShip":"JPN","cargo":{"cargoType":"LIQUID","weight":61512},"unloadDuration":{"day":0,"hour":13,"minute":8}},{"arriveTime":{"day":10,"hour":4,"minute":6},"nameShip":"CCN","cargo":{"cargoType":"LIQUID","weight":64548},"unloadDuration":{"day":0,"hour":13,"minute":47}},{"arriveTime":{"day":18,"hour":3,"minute":17},"nameShip":"ZH","cargo":{"cargoType":"LOOSE","weight":56034},"unloadDuration":{"day":0,"hour":14,"minute":22}},{"arriveTime":{"day":28,"hour":4,"minute":58},"nameShip":"QZB","cargo":{"cargoType":"LOOSE","weight":44091},"unloadDuration":{"day":0,"hour":11,"minute":18}},{"arriveTime":{"day":16,"hour":11,"minute":30},"nameShip":"UFX","cargo":{"cargoType":"LOOSE","weight":51772},"unloadDuration":{"day":0,"hour":13,"minute":16}},{"arriveTime":{"day":6,"hour":7,"minute":48},"nameShip":"YG","cargo":{"cargoType":"LOOSE","weight":40331},"unloadDuration":{"day":0,"hour":10,"minute":20}},{"arriveTime":{"day":17,"hour":15,"minute":27},"nameShip":"NHQ","cargo":{"cargoType":"CONTAINER","weight":2777},"unloadDuration":{"day":0,"hour":0,"minute":28}},{"arriveTime":{"day":0,"hour":2,"minute":27},"nameShip":"HQNN","cargo":{"cargoType":"LIQUID","weight":55707},"unloadDuration":{"day":0,"hour":11,"minute":54}},{"arriveTime":{"day":9,"hour":20,"minute":0},"nameShip":"FIW","cargo":{"cargoType":"LOOSE","weight":56384},"unloadDuration":{"day":0,"hour":14,"minute":27}},{"arriveTime":{"day":20,"hour":22,"minute":10},"nameShip":"CW","cargo":{"cargoType":"CONTAINER","weight":4110},"unloadDuration":{"day":0,"hour":0,"minute":41}},{"arriveTime":{"day":8,"hour":11,"minute":17},"nameShip":"HECR","cargo":{"cargoType":"LOOSE","weight":51509},"unloadDuration":{"day":0,"hour":13,"minute":12}},{"arriveTime":{"day":19,"hour":16,"minute":54},"nameShip":"EMJ","cargo":{"cargoType":"LOOSE","weight":57259},"unloadDuration":{"day":0,"hour":14,"minute":40}},{"arriveTime":{"day":24,"hour":2,"minute":33},"nameShip":"ZSEX","cargo":{"cargoType":"LOOSE","weight":45201},"unloadDuration":{"day":0,"hour":11,"minute":35}},{"arriveTime":{"day":28,"hour":14,"minute":17},"nameShip":"QEE","cargo":{"cargoType":"LOOSE","weight":49222},"unloadDuration":{"day":0,"hour":12,"minute":37}},{"arriveTime":{"day":28,"hour":16,"minute":48},"nameShip":"RZVN","cargo":{"cargoType":"LIQUID","weight":54149},"unloadDuration":{"day":0,"hour":11,"minute":34}},{"arriveTime":{"day":20,"hour":22,"minute":49},"nameShip":"YQDF","cargo":{"cargoType":"LOOSE","weight":40805},"unloadDuration":{"day":0,"hour":10,"minute":27}},{"arriveTime":{"day":12,"hour":7,"minute":50},"nameShip":"DGW","cargo":{"cargoType":"LIQUID","weight":56394},"unloadDuration":{"day":0,"hour":12,"minute":3}},{"arriveTime":{"day":29,"hour":18,"minute":55},"nameShip":"HAH","cargo":{"cargoType":"CONTAINER","weight":3039},"unloadDuration":{"day":0,"hour":0,"minute":30}},{"arriveTime":{"day":10,"hour":1,"minute":31},"nameShip":"GXC","cargo":{"cargoType":"LOOSE","weight":49949},"unloadDuration":{"day":0,"hour":12,"minute":48}},{"arriveTime":{"day":2,"hour":15,"minute":25},"nameShip":"PWVR","cargo":{"cargoType":"CONTAINER","weight":4451},"unloadDuration":{"day":0,"hour":0,"minute":44}},{"arriveTime":{"day":13,"hour":1,"minute":40},"nameShip":"YSYS","cargo":{"cargoType":"CONTAINER","weight":4126},"unloadDuration":{"day":0,"hour":0,"minute":41}},{"arriveTime":{"day":24,"hour":8,"minute":47},"nameShip":"DT","cargo":{"cargoType":"LIQUID","weight":50619},"unloadDuration":{"day":0,"hour":10,"minute":48}},{"arriveTime":{"day":26,"hour":16,"minute":39},"nameShip":"VF","cargo":{"cargoType":"LIQUID","weight":57714},"unloadDuration":{"day":0,"hour":12,"minute":19}},{"arriveTime":{"day":27,"hour":7,"minute":6},"nameShip":"XQS","cargo":{"cargoType":"LOOSE","weight":49954},"unloadDuration":{"day":0,"hour":12,"minute":48}},{"arriveTime":{"day":2,"hour":7,"minute":6},"nameShip":"RK","cargo":{"cargoType":"LIQUID","weight":55079},"unloadDuration":{"day":0,"hour":11,"minute":46}},{"arriveTime":{"day":13,"hour":12,"minute":41},"nameShip":"MUG","cargo":{"cargoType":"CONTAINER","weight":2122},"unloadDuration":{"day":0,"hour":0,"minute":21}},{"arriveTime":{"day":4,"hour":6,"minute":46},"nameShip":"PSLW","cargo":{"cargoType":"LIQUID","weight":66045},"unloadDuration":{"day":0,"hour":14,"minute":6}},{"arriveTime":{"day":14,"hour":6,"minute":35},"nameShip":"TFDL","cargo":{"cargoType":"CONTAINER","weight":5949},"unloadDuration":{"day":0,"hour":1,"minute":0}},{"arriveTime":{"day":29,"hour":10,"minute":58},"nameShip":"GOI","cargo":{"cargoType":"CONTAINER","weight":3178},"unloadDuration":{"day":0,"hour":0,"minute":32}},{"arriveTime":{"day":2,"hour":17,"minute":27},"nameShip":"DDKS","cargo":{"cargoType":"LIQUID","weight":63497},"unloadDuration":{"day":0,"hour":13,"minute":34}},{"arriveTime":{"day":1,"hour":1,"minute":49},"nameShip":"ALKD","cargo":{"cargoType":"CONTAINER","weight":4075},"unloadDuration":{"day":0,"hour":0,"minute":41}},{"arriveTime":{"day":2,"hour":17,"minute":50},"nameShip":"PAK","cargo":{"cargoType":"LOOSE","weight":43282},"unloadDuration":{"day":0,"hour":11,"minute":5}},{"arriveTime":{"day":25,"hour":8,"minute":23},"nameShip":"SYQJ","cargo":{"cargoType":"CONTAINER","weight":3638},"unloadDuration":{"day":0,"hour":0,"minute":36}},{"arriveTime":{"day":19,"hour":21,"minute":53},"nameShip":"PTW","cargo":{"cargoType":"LOOSE","weight":46517},"unloadDuration":{"day":0,"hour":11,"minute":55}},{"arriveTime":{"day":29,"hour":9,"minute":50},"nameShip":"FCBT","cargo":{"cargoType":"LIQUID","weight":56410},"unloadDuration":{"day":0,"hour":12,"minute":3}},{"arriveTime":{"day":22,"hour":14,"minute":17},"nameShip":"EDE","cargo":{"cargoType":"LIQUID","weight":65883},"unloadDuration":{"day":0,"hour":14,"minute":4}},{"arriveTime":{"day":7,"hour":11,"minute":44},"nameShip":"XVDA","cargo":{"cargoType":"LOOSE","weight":41039},"unloadDuration":{"day":0,"hour":10,"minute":31}},{"arriveTime":{"day":9,"hour":7,"minute":17},"nameShip":"EYE","cargo":{"cargoType":"LIQUID","weight":60523},"unloadDuration":{"day":0,"hour":12,"minute":55}},{"arriveTime":{"day":16,"hour":4,"minute":50},"nameShip":"EIFL","cargo":{"cargoType":"CONTAINER","weight":5682},"unloadDuration":{"day":0,"hour":0,"minute":57}},{"arriveTime":{"day":23,"hour":18,"minute":33},"nameShip":"LZ","cargo":{"cargoType":"LOOSE","weight":42899},"unloadDuration":{"day":0,"hour":10,"minute":59}},{"arriveTime":{"day":25,"hour":10,"minute":29},"nameShip":"GFXI","cargo":{"cargoType":"CONTAINER","weight":4277},"unloadDuration":{"day":0,"hour":0,"minute":43}},{"arriveTime":{"day":7,"hour":13,"minute":2},"nameShip":"VWX","cargo":{"cargoType":"CONTAINER","weight":3775},"unloadDuration":{"day":0,"hour":0,"minute":38}},{"arriveTime":{"day":2,"hour":18,"minute":36},"nameShip":"CQP","cargo":{"cargoType":"LIQUID","weight":58998},"unloadDuration":{"day":0,"hour":12,"minute":36}},{"arriveTime":{"day":25,"hour":15,"minute":18},"nameShip":"TAS","cargo":{"cargoType":"CONTAINER","weight":3884},"unloadDuration":{"day":0,"hour":0,"minute":39}},{"arriveTime":{"day":14,"hour":14,"minute":18},"nameShip":"MLT","cargo":{"cargoType":"LIQUID","weight":55782},"unloadDuration":{"day":0,"hour":11,"minute":55}},{"arriveTime":{"day":22,"hour":22,"minute":50},"nameShip":"DBNP","cargo":{"cargoType":"LIQUID","weight":50684},"unloadDuration":{"day":0,"hour":10,"minute":49}},{"arriveTime":{"day":12,"hour":9,"minute":57},"nameShip":"RFR","cargo":{"cargoType":"LOOSE","weight":53407},"unloadDuration":{"day":0,"hour":13,"minute":41}},{"arriveTime":{"day":7,"hour":20,"minute":14},"nameShip":"DF","cargo":{"cargoType":"CONTAINER","weight":3393},"unloadDuration":{"day":0,"hour":0,"minute":34}},{"arriveTime":{"day":9,"hour":10,"minute":21},"nameShip":"PQC","cargo":{"cargoType":"LIQUID","weight":61480},"unloadDuration":{"day":0,"hour":13,"minute":8}},{"arriveTime":{"day":1,"hour":12,"minute":25},"nameShip":"OPNR","cargo":{"cargoType":"CONTAINER","weight":5288},"unloadDuration":{"day":0,"hour":0,"minute":53}},{"arriveTime":{"day":8,"hour":4,"minute":35},"nameShip":"OR","cargo":{"cargoType":"LIQUID","weight":55378},"unloadDuration":{"day":0,"hour":11,"minute":49}},{"arriveTime":{"day":1,"hour":1,"minute":34},"nameShip":"AZVZ","cargo":{"cargoType":"LIQUID","weight":63004},"unloadDuration":{"day":0,"hour":13,"minute":27}},{"arriveTime":{"day":13,"hour":4,"minute":42},"nameShip":"OQX","cargo":{"cargoType":"LOOSE","weight":59361},"unloadDuration":{"day":0,"hour":15,"minute":13}},{"arriveTime":{"day":8,"hour":6,"minute":3},"nameShip":"HJQ","cargo":{"cargoType":"LIQUID","weight":55291},"unloadDuration":{"day":0,"hour":11,"minute":48}},{"arriveTime":{"day":26,"hour":19,"minute":29},"nameShip":"KGT","cargo":{"cargoType":"LOOSE","weight":54631},"unloadDuration":{"day":0,"hour":14,"minute":0}},{"arriveTime":{"day":9,"hour":4,"minute":20},"nameShip":"QN","cargo":{"cargoType":"LOOSE","weight":54129},"unloadDuration":{"day":0,"hour":13,"minute":52}},{"arriveTime":{"day":11,"hour":2,"minute":2},"nameShip":"VR","cargo":{"cargoType":"LOOSE","weight":40426},"unloadDuration":{"day":0,"hour":10,"minute":21}},{"arriveTime":{"day":17,"hour":23,"minute":1},"nameShip":"PV","cargo":{"cargoType":"LIQUID","weight":57395},"unloadDuration":{"day":0,"hour":12,"minute":15}},{"arriveTime":{"day":12,"hour":1,"minute":43},"nameShip":"GXUM","cargo":{"cargoType":"CONTAINER","weight":3261},"unloadDuration":{"day":0,"hour":0,"minute":32}},{"arriveTime":{"day":9,"hour":7,"minute":20},"nameShip":"RAR","cargo":{"cargoType":"LIQUID","weight":52240},"unloadDuration":{"day":0,"hour":11,"minute":9}},{"arriveTime":{"day":3,"hour":6,"minute":25},"nameShip":"SCJ","cargo":{"cargoType":"LIQUID","weight":54612},"unloadDuration":{"day":0,"hour":11,"minute":40}},{"arriveTime":{"day":28,"hour":19,"minute":11},"nameShip":"BOS","cargo":{"cargoType":"LOOSE","weight":52121},"unloadDuration":{"day":0,"hour":13,"minute":21}},{"arriveTime":{"day":20,"hour":21,"minute":21},"nameShip":"VMKA","cargo":{"cargoType":"LOOSE","weight":51632},"unloadDuration":{"day":0,"hour":13,"minute":14}},{"arriveTime":{"day":6,"hour":22,"minute":4},"nameShip":"NU","cargo":{"cargoType":"LIQUID","weight":64309},"unloadDuration":{"day":0,"hour":13,"minute":44}},{"arriveTime":{"day":9,"hour":23,"minute":28},"nameShip":"RI","cargo":{"cargoType":"LOOSE","weight":56111},"unloadDuration":{"day":0,"hour":14,"minute":23}},{"arriveTime":{"day":29,"hour":18,"minute":47},"nameShip":"EX","cargo":{"cargoType":"LIQUID","weight":53456},"unloadDuration":{"day":0,"hour":11,"minute":25}},{"arriveTime":{"day":6,"hour":15,"minute":23},"nameShip":"HOL","cargo":{"cargoType":"LIQUID","weight":65938},"unloadDuration":{"day":0,"hour":14,"minute":5}},{"arriveTime":{"day":25,"hour":19,"minute":18},"nameShip":"XF","cargo":{"cargoType":"CONTAINER","weight":4196},"unloadDuration":{"day":0,"hour":0,"minute":42}},{"arriveTime":{"day":4,"hour":10,"minute":5},"nameShip":"UG","cargo":{"cargoType":"LOOSE","weight":52824},"unloadDuration":{"day":0,"hour":13,"minute":32}},{"arriveTime":{"day":21,"hour":8,"minute":53},"nameShip":"DX","cargo":{"cargoType":"LIQUID","weight":57484},"unloadDuration":{"day":0,"hour":12,"minute":16}},{"arriveTime":{"day":15,"hour":6,"minute":15},"nameShip":"XY","cargo":{"cargoType":"LOOSE","weight":45158},"unloadDuration":{"day":0,"hour":11,"minute":34}},{"arriveTime":{"day":22,"hour":13,"minute":24},"nameShip":"WABU","cargo":{"cargoType":"LIQUID","weight":66894},"unloadDuration":{"day":0,"hour":14,"minute":17}},{"arriveTime":{"day":27,"hour":16,"minute":46},"nameShip":"VMD","cargo":{"cargoType":"LIQUID","weight":69150},"unloadDuration":{"day":0,"hour":14,"minute":46}},{"arriveTime":{"day":1,"hour":8,"minute":23},"nameShip":"GO","cargo":{"cargoType":"LIQUID","weight":53595},"unloadDuration":{"day":0,"hour":11,"minute":27}},{"arriveTime":{"day":14,"hour":14,"minute":13},"nameShip":"OPZI","cargo":{"cargoType":"LIQUID","weight":55117},"unloadDuration":{"day":0,"hour":11,"minute":46}},{"arriveTime":{"day":10,"hour":3,"minute":49},"nameShip":"IE","cargo":{"cargoType":"CONTAINER","weight":5280},"unloadDuration":{"day":0,"hour":0,"minute":53}},{"arriveTime":{"day":27,"hour":11,"minute":52},"nameShip":"QOG","cargo":{"cargoType":"CONTAINER","weight":4201},"unloadDuration":{"day":0,"hour":0,"minute":42}},{"arriveTime":{"day":1,"hour":2,"minute":33},"nameShip":"AOB","cargo":{"cargoType":"CONTAINER","weight":2191},"unloadDuration":{"day":0,"hour":0,"minute":22}},{"arriveTime":{"day":27,"hour":4,"minute":30},"nameShip":"FP","cargo":{"cargoType":"CONTAINER","weight":5833},"unloadDuration":{"day":0,"hour":0,"minute":58}},{"arriveTime":{"day":24,"hour":2,"minute":48},"nameShip":"OPWG","cargo":{"cargoType":"CONTAINER","weight":4462},"unloadDuration":{"day":0,"hour":0,"minute":45}},{"arriveTime":{"day":25,"hour":20,"minute":3},"nameShip":"LW","cargo":{"cargoType":"LIQUID","weight":59826},"unloadDuration":{"day":0,"hour":12,"minute":47}},{"arriveTime":{"day":22,"hour":3,"minute":51},"nameShip":"QQNR","cargo":{"cargoType":"LIQUID","weight":64717},"unloadDuration":{"day":0,"hour":13,"minute":49}},{"arriveTime":{"day":29,"hour":8,"minute":13},"nameShip":"LP","cargo":{"cargoType":"LIQUID","weight":69091},"unloadDuration":{"day":0,"hour":14,"minute":45}},{"arriveTime":{"day":22,"hour":11,"minute":4},"nameShip":"QSJB","cargo":{"cargoType":"LOOSE","weight":52330},"unloadDuration":{"day":0,"hour":13,"minute":25}},{"arriveTime":{"day":15,"hour":14,"minute":54},"nameShip":"CDB","cargo":{"cargoType":"LIQUID","weight":58254},"unloadDuration":{"day":0,"hour":12,"minute":26}},{"arriveTime":{"day":22,"hour":4,"minute":54},"nameShip":"FC","cargo":{"cargoType":"LIQUID","weight":52568},"unloadDuration":{"day":0,"hour":11,"minute":13}},{"arriveTime":{"day":22,"hour":3,"minute":2},"nameShip":"XQR","cargo":{"cargoType":"LIQUID","weight":61836},"unloadDuration":{"day":0,"hour":13,"minute":12}},{"arriveTime":{"day":1,"hour":0,"minute":43},"nameShip":"ZLU","cargo":{"cargoType":"LOOSE","weight":48022},"unloadDuration":{"day":0,"hour":12,"minute":18}},{"arriveTime":{"day":21,"hour":10,"minute":12},"nameShip":"GJYX","cargo":{"cargoType":"CONTAINER","weight":2855},"unloadDuration":{"day":0,"hour":0,"minute":28}},{"arriveTime":{"day":2,"hour":13,"minute":57},"nameShip":"YS","cargo":{"cargoType":"LIQUID","weight":51536},"unloadDuration":{"day":0,"hour":11,"minute":0}},{"arriveTime":{"day":27,"hour":6,"minute":4},"nameShip":"KCD","cargo":{"cargoType":"CONTAINER","weight":4013},"unloadDuration":{"day":0,"hour":0,"minute":40}},{"arriveTime":{"day":28,"hour":20,"minute":28},"nameShip":"DEJ","cargo":{"cargoType":"LIQUID","weight":64430},"unloadDuration":{"day":0,"hour":13,"minute":46}},{"arriveTime":{"day":17,"hour":5,"minute":54},"nameShip":"FL","cargo":{"cargoType":"LOOSE","weight":42816},"unloadDuration":{"day":0,"hour":10,"minute":58}},{"arriveTime":{"day":18,"hour":9,"minute":11},"nameShip":"RU","cargo":{"cargoType":"LOOSE","weight":57179},"unloadDuration":{"day":0,"hour":14,"minute":39}},{"arriveTime":{"day":1,"hour":15,"minute":42},"nameShip":"NR","cargo":{"cargoType":"CONTAINER","weight":5707},"unloadDuration":{"day":0,"hour":0,"minute":57}},{"arriveTime":{"day":22,"hour":5,"minute":27},"nameShip":"CFU","cargo":{"cargoType":"LOOSE","weight":44962},"unloadDuration":{"day":0,"hour":11,"minute":31}},{"arriveTime":{"day":1,"hour":17,"minute":1},"nameShip":"ELFG","cargo":{"cargoType":"LIQUID","weight":64094},"unloadDuration":{"day":0,"hour":13,"minute":41}},{"arriveTime":{"day":21,"hour":17,"minute":9},"nameShip":"CDD","cargo":{"cargoType":"LOOSE","weight":42922},"unloadDuration":{"day":0,"hour":11,"minute":0}},{"arriveTime":{"day":0,"hour":12,"minute":43},"nameShip":"YBAF","cargo":{"cargoType":"LOOSE","weight":49995},"unloadDuration":{"day":0,"hour":12,"minute":49}},{"arriveTime":{"day":19,"hour":23,"minute":48},"nameShip":"HA","cargo":{"cargoType":"LIQUID","weight":55623},"unloadDuration":{"day":0,"hour":11,"minute":53}},{"arriveTime":{"day":14,"hour":23,"minute":9},"nameShip":"IJFN","cargo":{"cargoType":"LIQUID","weight":66518},"unloadDuration":{"day":0,"hour":14,"minute":12}},{"arriveTime":{"day":16,"hour":16,"minute":33},"nameShip":"LH","cargo":{"cargoType":"LIQUID","weight":55848},"unloadDuration":{"day":0,"hour":11,"minute":56}},{"arriveTime":{"day":16,"hour":17,"minute":49},"nameShip":"HOHZ","cargo":{"cargoType":"LOOSE","weight":44504},"unloadDuration":{"day":0,"hour":11,"minute":24}},{"arriveTime":{"day":25,"hour":18,"minute":40},"nameShip":"QCJ","cargo":{"cargoType":"LIQUID","weight":55400},"unloadDuration":{"day":0,"hour":11,"minute":50}},{"arriveTime":{"day":5,"hour":23,"minute":38},"nameShip":"YR","cargo":{"cargoType":"CONTAINER","weight":5699},"unloadDuration":{"day":0,"hour":0,"minute":57}},{"arriveTime":{"day":18,"hour":4,"minute":24},"nameShip":"DBPO","cargo":{"cargoType":"LIQUID","weight":56970},"unloadDuration":{"day":0,"hour":12,"minute":10}},{"arriveTime":{"day":7,"hour":1,"minute":34},"nameShip":"ZZL","cargo":{"cargoType":"LOOSE","weight":43979},"unloadDuration":{"day":0,"hour":11,"minute":16}},{"arriveTime":{"day":22,"hour":6,"minute":57},"nameShip":"TH","cargo":{"cargoType":"LOOSE","weight":55404},"unloadDuration":{"day":0,"hour":14,"minute":12}},{"arriveTime":{"day":10,"hour":16,"minute":6},"nameShip":"MU","cargo":{"cargoType":"CONTAINER","weight":3635},"unloadDuration":{"day":0,"hour":0,"minute":36}},{"arriveTime":{"day":3,"hour":22,"minute":29},"nameShip":"PI","cargo":{"cargoType":"LIQUID","weight":58939},"unloadDuration":{"day":0,"hour":12,"minute":35}},{"arriveTime":{"day":5,"hour":20,"minute":52},"nameShip":"BRU","cargo":{"cargoType":"LIQUID","weight":60325},"unloadDuration":{"day":0,"hour":12,"minute":53}},{"arriveTime":{"day":17,"hour":2,"minute":57},"nameShip":"ZH","cargo":{"cargoType":"CONTAINER","weight":3656},"unloadDuration":{"day":0,"hour":0,"minute":36}},{"arriveTime":{"day":2,"hour":7,"minute":15},"nameShip":"NIWC","cargo":{"cargoType":"LIQUID","weight":53135},"unloadDuration":{"day":0,"hour":11,"minute":21}},{"arriveTime":{"day":1,"hour":20,"minute":5},"nameShip":"LOW","cargo":{"cargoType":"LOOSE","weight":42069},"unloadDuration":{"day":0,"hour":10,"minute":47}},{"arriveTime":{"day":18,"hour":15,"minute":7},"nameShip":"GNBA","cargo":{"cargoType":"LIQUID","weight":59669},"unloadDuration":{"day":0,"hour":12,"minute":44}},{"arriveTime":{"day":19,"hour":23,"minute":10},"nameShip":"LYC","cargo":{"cargoType":"CONTAINER","weight":4293},"unloadDuration":{"day":0,"hour":0,"minute":43}},{"arriveTime":{"day":20,"hour":5,"minute":23},"nameShip":"KZ","cargo":{"cargoType":"CONTAINER","weight":2533},"unloadDuration":{"day":0,"hour":0,"minute":25}},{"arriveTime":{"day":8,"hour":9,"minute":18},"nameShip":"FCLM","cargo":{"cargoType":"LOOSE","weight":50717},"unloadDuration":{"day":0,"hour":13,"minute":0}},{"arriveTime":{"day":1,"hour":23,"minute":45},"nameShip":"FAG","cargo":{"cargoType":"CONTAINER","weight":5575},"unloadDuration":{"day":0,"hour":0,"minute":56}},{"arriveTime":{"day":18,"hour":6,"minute":55},"nameShip":"BC","cargo":{"cargoType":"LIQUID","weight":63035},"unloadDuration":{"day":0,"hour":13,"minute":28}},{"arriveTime":{"day":14,"hour":0,"minute":19},"nameShip":"DPZ","cargo":{"cargoType":"CONTAINER","weight":2966},"unloadDuration":{"day":0,"hour":0,"minute":29}},{"arriveTime":{"day":16,"hour":6,"minute":12},"nameShip":"CEKQ","cargo":{"cargoType":"CONTAINER","weight":3249},"unloadDuration":{"day":0,"hour":0,"minute":32}},{"arriveTime":{"day":5,"hour":20,"minute":29},"nameShip":"OMH","cargo":{"cargoType":"CONTAINER","weight":4614},"unloadDuration":{"day":0,"hour":0,"minute":46}},{"arriveTime":{"day":4,"hour":5,"minute":7},"nameShip":"WBZV","cargo":{"cargoType":"LOOSE","weight":47195},"unloadDuration":{"day":0,"hour":12,"minute":6}},{"arriveTime":{"day":5,"hour":14,"minute":19},"nameShip":"SKIL","cargo":{"cargoType":"CONTAINER","weight":5448},"unloadDuration":{"day":0,"hour":0,"minute":55}},{"arriveTime":{"day":25,"hour":17,"minute":2},"nameShip":"SHW","cargo":{"cargoType":"LIQUID","weight":60234},"unloadDuration":{"day":0,"hour":12,"minute":52}},{"arriveTime":{"day":17,"hour":18,"minute":44},"nameShip":"VCLY","cargo":{"cargoType":"CONTAINER","weight":3959},"unloadDuration":{"day":0,"hour":0,"minute":39}},{"arriveTime":{"day":11,"hour":10,"minute":2},"nameShip":"HH","cargo":{"cargoType":"LOOSE","weight":57892},"unloadDuration":{"day":0,"hour":14,"minute":50}},{"arriveTime":{"day":25,"hour":8,"minute":59},"nameShip":"RK","cargo":{"cargoType":"LIQUID","weight":56159},"unloadDuration":{"day":0,"hour":11,"minute":59}},{"arriveTime":{"day":6,"hour":22,"minute":12},"nameShip":"EY","cargo":{"cargoType":"LIQUID","weight":52011},"unloadDuration":{"day":0,"hour":11,"minute":6}},{"arriveTime":{"day":23,"hour":5,"minute":25},"nameShip":"TABX","cargo":{"cargoType":"LIQUID","weight":66135},"unloadDuration":{"day":0,"hour":14,"minute":7}},{"arriveTime":{"day":10,"hour":7,"minute":20},"nameShip":"MSA","cargo":{"cargoType":"LOOSE","weight":53554},"unloadDuration":{"day":0,"hour":13,"minute":43}},{"arriveTime":{"day":14,"hour":5,"minute":39},"nameShip":"NI","cargo":{"cargoType":"LIQUID","weight":61783},"unloadDuration":{"day":0,"hour":13,"minute":12}},{"arriveTime":{"day":20,"hour":22,"minute":25},"nameShip":"EAOX","cargo":{"cargoType":"LOOSE","weight":48240},"unloadDuration":{"day":0,"hour":12,"minute":22}},{"arriveTime":{"day":16,"hour":19,"minute":14},"nameShip":"GLTX","cargo":{"cargoType":"LIQUID","weight":50339},"unloadDuration":{"day":0,"hour":10,"minute":45}},{"arriveTime":{"day":20,"hour":8,"minute":58},"nameShip":"LJ","cargo":{"cargoType":"CONTAINER","weight":2738},"unloadDuration":{"day":0,"hour":0,"minute":27}},{"arriveTime":{"day":26,"hour":8,"minute":27},"nameShip":"LWWL","cargo":{"cargoType":"CONTAINER","weight":3851},"unloadDuration":{"day":0,"hour":0,"minute":38}},{"arriveTime":{"day":5,"hour":10,"minute":15},"nameShip":"EYLO","cargo":{"cargoType":"LOOSE","weight":49034},"unloadDuration":{"day":0,"hour":12,"minute":34}},{"arriveTime":{"day":17,"hour":4,"minute":46},"nameShip":"ZV","cargo":{"cargoType":"LOOSE","weight":56542},"unloadDuration":{"day":0,"hour":14,"minute":29}},{"arriveTime":{"day":23,"hour":12,"minute":45},"nameShip":"GQ","cargo":{"cargoType":"LIQUID","weight":58829},"unloadDuration":{"day":0,"hour":12,"minute":34}},{"arriveTime":{"day":23,"hour":9,"minute":28},"nameShip":"EH","cargo":{"cargoType":"CONTAINER","weight":4925},"unloadDuration":{"day":0,"hour":0,"minute":49}},{"arriveTime":{"day":14,"hour":12,"minute":38},"nameShip":"SLN","cargo":{"cargoType":"LOOSE","weight":44899},"unloadDuration":{"day":0,"hour":11,"minute":30}},{"arriveTime":{"day":17,"hour":19,"minute":10},"nameShip":"MHXT","cargo":{"cargoType":"LOOSE","weight":40409},"unloadDuration":{"day":0,"hour":10,"minute":21}},{"arriveTime":{"day":3,"hour":18,"minute":13},"nameShip":"SC","cargo":{"cargoType":"CONTAINER","weight":5845},"unloadDuration":{"day":0,"hour":0,"minute":59}},{"arriveTime":{"day":4,"hour":22,"minute":19},"nameShip":"JIRC","cargo":{"cargoType":"LIQUID","weight":52803},"unloadDuration":{"day":0,"hour":11,"minute":16}},{"arriveTime":{"day":29,"hour":14,"minute":45},"nameShip":"RTJ","cargo":{"cargoType":"CONTAINER","weight":4369},"unloadDuration":{"day":0,"hour":0,"minute":44}},{"arriveTime":{"day":22,"hour":6,"minute":15},"nameShip":"HRP","cargo":{"cargoType":"LOOSE","weight":45027},"unloadDuration":{"day":0,"hour":11,"minute":32}},{"arriveTime":{"day":17,"hour":13,"minute":20},"nameShip":"YY","cargo":{"cargoType":"LIQUID","weight":54816},"unloadDuration":{"day":0,"hour":11,"minute":42}},{"arriveTime":{"day":8,"hour":20,"minute":33},"nameShip":"VY","cargo":{"cargoType":"LIQUID","weight":50534},"unloadDuration":{"day":0,"hour":10,"minute":47}},{"arriveTime":{"day":12,"hour":2,"minute":7},"nameShip":"MWYZ","cargo":{"cargoType":"CONTAINER","weight":3614},"unloadDuration":{"day":0,"hour":0,"minute":36}},{"arriveTime":{"day":28,"hour":23,"minute":7},"nameShip":"OY","cargo":{"cargoType":"LIQUID","weight":54783},"unloadDuration":{"day":0,"hour":11,"minute":42}},{"arriveTime":{"day":15,"hour":2,"minute":14},"nameShip":"FL","cargo":{"cargoType":"LIQUID","weight":59113},"unloadDuration":{"day":0,"hour":12,"minute":37}},{"arriveTime":{"day":4,"hour":2,"minute":7},"nameShip":"NPRF","cargo":{"cargoType":"LIQUID","weight":51456},"unloadDuration":{"day":0,"hour":10,"minute":59}},{"arriveTime":{"day":7,"hour":22,"minute":37},"nameShip":"ZKM","cargo":{"cargoType":"LIQUID","weight":54889},"unloadDuration":{"day":0,"hour":11,"minute":43}},{"arriveTime":{"day":0,"hour":5,"minute":15},"nameShip":"SGPG","cargo":{"cargoType":"LIQUID","weight":60692},"unloadDuration":{"day":0,"hour":12,"minute":58}},{"arriveTime":{"day":22,"hour":10,"minute":15},"nameShip":"ONA","cargo":{"cargoType":"CONTAINER","weight":4581},"unloadDuration":{"day":0,"hour":0,"minute":46}},{"arriveTime":{"day":13,"hour":1,"minute":24},"nameShip":"ZI","cargo":{"cargoType":"LOOSE","weight":42575},"unloadDuration":{"day":0,"hour":10,"minute":55}},{"arriveTime":{"day":2,"hour":4,"minute":22},"nameShip":"LZG","cargo":{"cargoType":"CONTAINER","weight":5387},"unloadDuration":{"day":0,"hour":0,"minute":54}},{"arriveTime":{"day":0,"hour":6,"minute":2},"nameShip":"XCM","cargo":{"cargoType":"CONTAINER","weight":4871},"unloadDuration":{"day":0,"hour":0,"minute":49}},{"arriveTime":{"day":27,"hour":10,"minute":25},"nameShip":"MTYP","cargo":{"cargoType":"LOOSE","weight":50254},"unloadDuration":{"day":0,"hour":12,"minute":53}},{"arriveTime":{"day":16,"hour":12,"minute":51},"nameShip":"MDNM","cargo":{"cargoType":"CONTAINER","weight":2354},"unloadDuration":{"day":0,"hour":0,"minute":23}},{"arriveTime":{"day":9,"hour":21,"minute":22},"nameShip":"HSM","cargo":{"cargoType":"LIQUID","weight":52144},"unloadDuration":{"day":0,"hour":11,"minute":8}},{"arriveTime":{"day":11,"hour":4,"minute":54},"nameShip":"MMB","cargo":{"cargoType":"LIQUID","weight":59650},"unloadDuration":{"day":0,"hour":12,"minute":44}},{"arriveTime":{"day":17,"hour":16,"minute":44},"nameShip":"LWHW","cargo":{"cargoType":"LIQUID","weight":68622},"unloadDuration":{"day":0,"hour":14,"minute":39}},{"arriveTime":{"day":3,"hour":21,"minute":46},"nameShip":"YJSD","cargo":{"cargoType":"LIQUID","weight":54424},"unloadDuration":{"day":0,"hour":11,"minute":37}},{"arriveTime":{"day":27,"hour":7,"minute":54},"nameShip":"CSKQ","cargo":{"cargoType":"LOOSE","weight":50686},"unloadDuration":{"day":0,"hour":12,"minute":59}},{"arriveTime":{"day":21,"hour":8,"minute":51},"nameShip":"URJ","cargo":{"cargoType":"LIQUID","weight":61284},"unloadDuration":{"day":0,"hour":13,"minute":5}},{"arriveTime":{"day":24,"hour":4,"minute":46},"nameShip":"AB","cargo":{"cargoType":"LOOSE","weight":47817},"unloadDuration":{"day":0,"hour":12,"minute":15}},{"arriveTime":{"day":20,"hour":0,"minute":5},"nameShip":"DH","cargo":{"cargoType":"LOOSE","weight":43833},"unloadDuration":{"day":0,"hour":11,"minute":14}},{"arriveTime":{"day":0,"hour":17,"minute":1},"nameShip":"GBL","cargo":{"cargoType":"LIQUID","weight":53626},"unloadDuration":{"day":0,"hour":11,"minute":27}},{"arriveTime":{"day":24,"hour":15,"minute":38},"nameShip":"TUB","cargo":{"cargoType":"LOOSE","weight":57427},"unloadDuration":{"day":0,"hour":14,"minute":43}}]}